persephone_client/__init__.py
persephone_client/build_helpers.py
persephone_client/client.py
persephone_client/persephone_cli.py
persephone_client_py-0.0.2.dist-info/DESCRIPTION.rst
persephone_client_py-0.0.2.dist-info/METADATA
persephone_client_py-0.0.2.dist-info/RECORD
persephone_client_py-0.0.2.dist-info/WHEEL
persephone_client_py-0.0.2.dist-info/entry_points.txt
persephone_client_py-0.0.2.dist-info/metadata.json
persephone_client_py-0.0.2.dist-info/top_level.txt
