Metadata-Version: 2.0
Name: persephone-client-py
Version: 0.0.2
Summary: A Python client for the Persephone REST API
Home-page: http://github.com/karamanolev/persephone-client-py
Author: Ivailo Karamanolev
Author-email: ivailo@karamanolev.com
License: MIT
Keywords: python visual-regression-testing
Platform: UNKNOWN
Classifier: Development Status :: 3 - Alpha
Classifier: Intended Audience :: Developers
Classifier: License :: OSI Approved :: MIT License
Classifier: Programming Language :: Python :: 3 :: Only
Classifier: Topic :: Software Development :: Testing
Requires-Dist: requests
